{
  "name": "Line",
  "route": "line",
  "authLevel": "none",
  "properties": {
    "order": {
      "type": "Number"
    },
    "name": {
      "type": "String"
    },
    "shortName": {
      "type": "String"
    },
    "colour": {
      "type": "String"
    },
    "fontColour": {
      "type": "String"
    },
    "year": {
      "type": "Number"
    },
    "distance": {
      "type": "Number"
    },
    "stationsAmount": {
      "type": "Number"
    },
    "startStations": {
      "type": "[Station]"
    },
    "connections": {
      "type": "[Connection]",
      "propertyMatch": "line"
    }
  }
}